bot_vision/__init__.py
bot_vision/exceptions.py
bot_vision/core/__init__.py
bot_vision/core/image_processing.py
bot_vision/core/keyboard_commands.py
bot_vision/core/ocr_engine.py
bot_vision/core/overlay.py
bot_vision/core/overlay_new.py
bot_vision/core/relative_image.py
bot_vision/core/task_executor.py
bot_vision/core/virtual_mouse.py
bot_vision/core/wait_manager.py
bot_vision/utils/__init__.py
bot_vision/utils/config.py
bot_vision/utils/text_filters.py
bot_vision_suite-1.3.1.dist-info/licenses/LICENSE
bot_vision_suite-1.3.1.dist-info/METADATA
bot_vision_suite-1.3.1.dist-info/WHEEL
bot_vision_suite-1.3.1.dist-info/top_level.txt
bot_vision_suite-1.3.1.dist-info/RECORD
