Metadata-Version: 2.4
Name: bot-vision-suite
Version: 1.3.1
Summary: Biblioteca Python avançada para automação de interface gráfica com OCR multi-técnica, detecção de imagens robusta e sistema de backtrack inteligente
Author-email: Automation Suite Developer <matheuszwilkdev@gmail.com>
License-Expression: MIT
Project-URL: Homepage, https://github.com/matheuszwilk/bot-vision-suite
Project-URL: Documentation, https://github.com/matheuszwilk/bot-vision-suite#readme
Project-URL: Repository, https://github.com/matheuszwilk/bot-vision-suite.git
Project-URL: Bug Tracker, https://github.com/matheuszwilk/bot-vision-suite/issues
Keywords: automation,gui,ocr,image-recognition,rpa,bot,desktop-automation
Classifier: Development Status :: 4 - Beta
Classifier: Intended Audience :: Developers
Classifier: Operating System :: OS Independent
Classifier: Programming Language :: Python :: 3.8
Classifier: Programming Language :: Python :: 3.9
Classifier: Programming Language :: Python :: 3.10
Classifier: Programming Language :: Python :: 3.11
Classifier: Programming Language :: Python :: 3.12
Classifier: Topic :: Software Development :: Libraries :: Python Modules
Classifier: Topic :: Software Development :: Testing
Classifier: Topic :: Desktop Environment
Requires-Python: >=3.8
License-File: LICENSE
Requires-Dist: PyAutoGUI>=0.9.54
Requires-Dist: pytesseract>=0.3.0
Requires-Dist: opencv-python>=4.9.0
Requires-Dist: Pillow>=10.0.0
Requires-Dist: numpy>=1.24.0
Requires-Dist: pyperclip>=1.8.2
Provides-Extra: dev
Requires-Dist: pytest>=7.0.0; extra == "dev"
Requires-Dist: pytest-cov>=4.0.0; extra == "dev"
Requires-Dist: black>=22.0.0; extra == "dev"
Requires-Dist: flake8>=5.0.0; extra == "dev"
Provides-Extra: automation
Requires-Dist: keyboard>=0.13.5; extra == "automation"
Requires-Dist: MouseInfo>=0.1.3; extra == "automation"
Requires-Dist: setuptools; extra == "automation"
Requires-Dist: pandas>=1.0.0; extra == "automation"
Provides-Extra: ai
Requires-Dist: openai>=1.0.0; extra == "ai"
Provides-Extra: web
Requires-Dist: webdriver-manager>=4.0.0; extra == "web"
Dynamic: license-file
